{
	"dataset": {
		"reportID":"spicegarden",
		"defaultSort":"Artefact_Number",
		"name":"14th-Century Small Finds",
		"id":"14csmallfinds",
		"data":
		[
			{"Artefact_Number":"FTCSGG001","Unit":"I","Spit":"1","Lot":"4","Weight":"1","Quantities_in_number_of_sherds":5,"Type_of_Ware":"Glass (14th century)","Vessel_Part":"","Vessel_Type":"","Length":"","Breadth_Width":"","Thickness":"","Diameter":"","Excavation_Date":"2010-04-15T16:00:00.000Z","Remarks":"Fragments of a glass shard and bangle (c. 14th century)"},{"Artefact_Number":"FTCSGG002","Unit":"III","Spit":"1","Lot":"3","Weight":"1","Quantities_in_number_of_sherds":1,"Type_of_Ware":"Glass (14th century)","Vessel_Part":"Rim","Vessel_Type":"Vase","Length":1.8,"Breadth_Width":0.6,"Thickness":0.1,"Diameter":"","Excavation_Date":"","Remarks":"Glass rim shard with inlaid white band on the interior and exterior of the rim. The body is maroon, and the rim top is blue. "},{"Artefact_Number":"FTCSGG003","Unit":"III","Spit":"1","Lot":"3","Weight":"1","Quantities_in_number_of_sherds":1,"Type_of_Ware":"Glass (14th century)","Vessel_Part":"Body","Vessel_Type":"Bangle","Length":1.6,"Breadth_Width":"","Thickness":0.5,"Diameter":"","Excavation_Date":"","Remarks":"Light green bangle."},{"Artefact_Number":"FTCSGG004","Unit":"III","Spit":"1","Lot":"3","Weight":"1","Quantities_in_number_of_sherds":1,"Type_of_Ware":"Glass (14th century)","Vessel_Part":"Body","Vessel_Type":"Bangle","Length":3,"Breadth_Width":"","Thickness":0.4,"Diameter":"","Excavation_Date":"2010-04-30T16:00:00.000Z","Remarks":"Light green bangle."},{"Artefact_Number":"FTCSGG005","Unit":"III","Spit":"2","Lot":"3","Weight":"1","Quantities_in_number_of_sherds":1,"Type_of_Ware":"Glass (14th century)","Vessel_Part":"Body","Vessel_Type":"Vase","Length":1.7,"Breadth_Width":1.6,"Thickness":0.4,"Diameter":"","Excavation_Date":"2010-05-02T16:00:00.000Z","Remarks":"Inlaid green and yellow glass on opaque white body."},{"Artefact_Number":"FTCSGG006","Unit":"II","Spit":"1","Lot":"3","Weight":"1","Quantities_in_number_of_sherds":1,"Type_of_Ware":"Glass (14th century)","Vessel_Part":"","Vessel_Type":"Bead","Length":"","Breadth_Width":"","Thickness":0.7,"Diameter":0.7,"Excavation_Date":"2010-04-08T16:00:00.000Z","Remarks":"Blue glass bead"},{"Artefact_Number":"FTCSGGW0379","Unit":"3","Spit":"1","Lot":"1","Weight":"","Quantities_in_number_of_sherds":"","Type_of_Ware":"","Vessel_Part":"Body","Vessel_Type":"","Length":"","Breadth_Width":"","Thickness":"","Diameter":"","Excavation_Date":"","Remarks":""},{"Artefact_Number":"FTCSGGW0380","Unit":"3","Spit":"2","Lot":"3","Weight":"","Quantities_in_number_of_sherds":"","Type_of_Ware":"","Vessel_Part":"Body","Vessel_Type":"","Length":"","Breadth_Width":"","Thickness":"","Diameter":"","Excavation_Date":"","Remarks":""},{"Artefact_Number":"FTCSGGW0381","Unit":"","Spit":"","Lot":"","Weight":"","Quantities_in_number_of_sherds":"","Type_of_Ware":"","Vessel_Part":"","Vessel_Type":"","Length":"","Breadth_Width":"","Thickness":"","Diameter":"","Excavation_Date":"","Remarks":""},{"Artefact_Number":"FTCSGGW0382","Unit":"","Spit":"","Lot":"","Weight":"","Quantities_in_number_of_sherds":"","Type_of_Ware":"","Vessel_Part":"","Vessel_Type":"","Length":"","Breadth_Width":"","Thickness":"","Diameter":"","Excavation_Date":"","Remarks":""},{"Artefact_Number":"FTCSGGW0383","Unit":"","Spit":"","Lot":"","Weight":"","Quantities_in_number_of_sherds":"","Type_of_Ware":"","Vessel_Part":"","Vessel_Type":"","Length":"","Breadth_Width":"","Thickness":"","Diameter":"","Excavation_Date":"","Remarks":""},{"Artefact_Number":"FTCSGGW0384","Unit":"","Spit":"","Lot":"","Weight":"","Quantities_in_number_of_sherds":"","Type_of_Ware":"","Vessel_Part":"","Vessel_Type":"","Length":"","Breadth_Width":"","Thickness":"","Diameter":"","Excavation_Date":"","Remarks":""},{"Artefact_Number":"FTCSGGW0385","Unit":"","Spit":"","Lot":"","Weight":"","Quantities_in_number_of_sherds":"","Type_of_Ware":"","Vessel_Part":"","Vessel_Type":"","Length":"","Breadth_Width":"","Thickness":"","Diameter":"","Excavation_Date":"","Remarks":""},{"Artefact_Number":"FTCSGGW0386","Unit":"","Spit":"","Lot":"","Weight":"","Quantities_in_number_of_sherds":"","Type_of_Ware":"","Vessel_Part":"","Vessel_Type":"","Length":"","Breadth_Width":"","Thickness":"","Diameter":"","Excavation_Date":"","Remarks":""},{"Artefact_Number":"FTCSGM0166","Unit":"III","Spit":"2","Lot":"3","Weight":"6","Quantities_in_number_of_sherds":2,"Type_of_Ware":"Bronze/Metal (14th century)","Vessel_Part":"Rim","Vessel_Type":"","Length":2.8,"Breadth_Width":2.6,"Thickness":0.3,"Diameter":"","Excavation_Date":"2010-05-02T16:00:00.000Z","Remarks":"Bronze vessel fragments"},{"Artefact_Number":"FTCSGM0167","Unit":"III","Spit":"2","Lot":"3","Weight":"9","Quantities_in_number_of_sherds":1,"Type_of_Ware":"Bronze/Metal (14th century)","Vessel_Part":"Body","Vessel_Type":"","Length":3.9,"Breadth_Width":3,"Thickness":0.3,"Diameter":"","Excavation_Date":"","Remarks":"Bronze vessel fragment"},{"Artefact_Number":"FTCSGM0168","Unit":"IV","Spit":"","Lot":"3","Weight":"","Quantities_in_number_of_sherds":1,"Type_of_Ware":"Bronze/Metal (14th century)","Vessel_Part":"","Vessel_Type":"Coin","Length":3.5,"Breadth_Width":3.5,"Thickness":"","Diameter":"","Excavation_Date":"2010-04-28T16:00:00.000Z","Remarks":"14th-century Yuan coin"},{"Artefact_Number":"FTCSGS021","Unit":"IV","Spit":"1","Lot":"3","Weight":"1161","Quantities_in_number_of_sherds":1,"Type_of_Ware":"Stone","Vessel_Part":"","Vessel_Type":"","Length":14.9,"Breadth_Width":8,"Thickness":7.2,"Diameter":"","Excavation_Date":"2010-04-25T16:00:00.000Z","Remarks":"Sandstone. In the shape of possibly the thigh of a statue."}
			],
			"fields":
			[
				{"fieldKey":"Artefact_Number","fieldName":"Artefact Number"},{"fieldKey":"Unit","fieldName":"Unit"},{"fieldKey":"Spit","fieldName":"Spit"},{"fieldKey":"Lot","fieldName":"Lot"},{"fieldKey":"Weight","fieldName":"Weight","fieldUnit":"g"},{"fieldKey":"Quantities_in_number_of_sherds","fieldName":"Quantities in number of sherds"},{"fieldKey":"Type_of_Ware","fieldName":"Type of Ware","fieldValues":["19th–20th c Chinese Porcelain","19th–20th c Chinese Stoneware","19th–20th c Construction Tiles","19th–20th c European Porcelain","19th–20th c European Stoneware","Blue & White - Jingdezhen","Blue & White - Others","Brick (14th century)","Brittle Stoneware","Bronze/Metal (14th century)","Buff Stoneware","Fine Paste","Glass (14th century)","Greenware - Longquan","Greenware - Xicun","Greenware - Others","Iron-spotted Qingbai","Mercury Jar","Stone","Stoneware - others","Stoneware - Sukhothai/Sawankhalok","Tempered","White - Dehua","White - Ding","White - Others"]},{"fieldKey":"Vessel_Part","fieldName":"Vessel Part","fieldValues":["Base","Bead","Body","Body (deco)","Carination","Eaveboard tile","Foot rim","Handle","Knob","Lid","Lug","Mouth","Mouth & Lug","Neck","Rim","Rim & Base (Complete Profile)","Shoulder","Spout","Unknown"]},{"fieldKey":"Vessel_Type","fieldName":"Vessel Type","fieldValues":["Bangle","Bead","Bowl","Brick","Coin","Covered box","Cup","Crucible","Eaveboard tile","Ewer","Figurine","Jar","Jarlet","Kendi","Large bowl","Lid","Long necked vessel","Medium bowl","Open pot","Plate bowl","Pot","Shallow bowl","Small bowl","Stand","Stove","Vase","Unknown"]},{"fieldKey":"Length","fieldName":"Length","fieldUnit":"cm"},{"fieldKey":"Breadth_Width","fieldName":"Breadth/Width","fieldUnit":"cm"},{"fieldKey":"Thickness","fieldName":"Thickness","fieldUnit":"cm"},{"fieldKey":"Diameter","fieldName":"Diameter","fieldUnit":"cm"},
					{"fieldKey":"Excavation_Date","fieldName":"Excavation Date","fieldType":"date"},
					{"fieldKey":"Remarks","fieldName":"Remarks","fieldType":"text"}
					]
					}
				}